{
  "posts": [
    {
      "id": 8,
      "firstName": "Corporis similique e",
      "lastName": "Porro repellendus C",
      "email": "vozacite@mailinator.com",
      "mobile": "Nisi mollit mollitia",
      "salary": "Nulla excepturi exce"
    },
    {
      "id": 10,
      "firstName": "Praesentium lorem ex",
      "lastName": "Consequatur sit in q",
      "email": "viky@mailinator.com",
      "mobile": "Ea ea veniam possim",
      "salary": "Aut quia autem aliqu"
    },
    {
      "id": 11,
      "firstName": "Fugiat lorem nisi cu",
      "lastName": "Enim libero ut totam",
      "email": "vunuzy@mailinator.com",
      "mobile": "Pariatur Aut velit ",
      "salary": "Dolor id nihil conse"
    },
    {
      "id": 12,
      "firstName": "Iste voluptatum et p",
      "lastName": "Dolorem ullamco et q",
      "email": "zumuzufy@mailinator.com",
      "mobile": "Culpa iusto commodi ",
      "salary": "Sunt nulla consequat"
    },
    {
      "id": 13,
      "firstName": "Cupidatat ut vel vol",
      "lastName": "Unde irure molestias",
      "email": "qepufyholi@mailinator.com",
      "mobile": "Id adipisicing imped",
      "salary": "Voluptas aliquam sun"
    },
    {
      "id": 14,
      "firstName": "Eiusmod accusamus se",
      "lastName": "Temporibus voluptas ",
      "email": "ruvanyjije@mailinator.com",
      "mobile": "Voluptatem rerum non",
      "salary": "Excepteur amet cons"
    }
  ],
  "comments": [],
  "profile": {
    "name": "typicode"
  }
}